sonicare_bletb/__init__.py
sonicare_bletb/const.py
sonicare_bletb/models.py
sonicare_bletb/py.typed
sonicare_bletb/sonicare_bletb.py
sonicare_bletb-0.0.8.dist-info/LICENSE
sonicare_bletb-0.0.8.dist-info/METADATA
sonicare_bletb-0.0.8.dist-info/WHEEL
sonicare_bletb-0.0.8.dist-info/RECORD
